<?xml version="1.0" encoding="utf-8"?>
<manifest xmlns:android="http://schemas.android.com/apk/res/android"
    package="org.kivy.skkutimetable.doublecheck">
    
    <!-- ê¸°ì¡´ ê¶Œí•œë“¤ -->
    <uses-permission android:name="android.permission.INTERNET" />
    <uses-permission android:name="android.permission.WRITE_EXTERNAL_STORAGE" />
    <uses-permission android:name="android.permission.READ_EXTERNAL_STORAGE" />
    
    <!-- ðŸ”¥ ì•ŒëžŒ ê´€ë ¨ ê¶Œí•œë“¤ (ê°•í™”) -->
    <uses-permission android:name="android.permission.WAKE_LOCK" />
    <uses-permission android:name="android.permission.VIBRATE" />
    <uses-permission android:name="android.permission.SET_ALARM" />
    <uses-permission android:name="android.permission.SCHEDULE_EXACT_ALARM" />
    <uses-permission android:name="android.permission.USE_EXACT_ALARM" />
    <uses-permission android:name="android.permission.RECEIVE_BOOT_COMPLETED" />
    <uses-permission android:name="android.permission.FOREGROUND_SERVICE" />
    <uses-permission android:name="android.permission.POST_NOTIFICATIONS" />
    
    <application
        android:label="@string/app_name"
        android:icon="@mipmap/icon"
        android:allowBackup="true"
        android:theme="@android:style/Theme.NoTitleBar"
        android:hardwareAccelerated="true"
        android:extractNativeLibs="true"
        android:requestLegacyExternalStorage="true">
        
        <!-- ê¸°ì¡´ PythonActivity -->
        <activity android:name="org.kivy.android.PythonActivity"
            android:exported="true"
            android:label="@string/app_name"
            android:theme="@android:style/Theme.NoTitleBar.Fullscreen"
            android:configChanges="keyboardHidden|orientation|screenSize"
            android:screenOrientation="portrait">
            <intent-filter>
                <action android:name="android.intent.action.MAIN" />
                <category android:name="android.intent.category.LAUNCHER" />
            </intent-filter>
        </activity>
        
        <!-- ðŸ”¥ í•µì‹¬ ìˆ˜ì •: ì „ì²´ í´ëž˜ìŠ¤ëª… ì‚¬ìš© -->
        <receiver android:name="org.kivy.skkutimetable.doublecheck.AlarmReceiver"
            android:enabled="true"
            android:exported="true"
            android:directBootAware="true">
            
            <!-- ðŸ”¥ ë‹¤ì–‘í•œ Intent í•„í„° ì¶”ê°€ -->
            <intent-filter android:priority="1000">
                <action android:name="android.intent.action.BOOT_COMPLETED" />
                <action android:name="android.intent.action.MY_PACKAGE_REPLACED" />
                <action android:name="android.intent.action.PACKAGE_REPLACED" />
                <data android:scheme="package" />
            </intent-filter>
            
            <!-- ðŸ”¥ ì»¤ìŠ¤í…€ ì•ŒëžŒ ì•¡ì…˜ -->
            <intent-filter>
                <action android:name="org.kivy.skkutimetable.doublecheck.ALARM_ACTION" />
            </intent-filter>
            
            <!-- ðŸ”¥ ì¼ë°˜ ë¸Œë¡œë“œìºìŠ¤íŠ¸ -->
            <intent-filter>
                <action android:name="android.intent.action.USER_PRESENT" />
            </intent-filter>
        </receiver>
        
        <!-- ðŸ”¥ AlarmServiceë„ ì „ì²´ í´ëž˜ìŠ¤ëª… ì‚¬ìš© -->
        <service android:name="org.kivy.skkutimetable.doublecheck.AlarmService"
            android:enabled="true"
            android:exported="false"
            android:foregroundServiceType="specialUse">
        </service>
        
    </application>
</manifest>
